hueclientrest/__init__.py
hueclientrest/core.py
hueclientrest-0.2.0.dist-info/licenses/LICENSE
hueclientrest-0.2.0.dist-info/METADATA
hueclientrest-0.2.0.dist-info/WHEEL
hueclientrest-0.2.0.dist-info/top_level.txt
hueclientrest-0.2.0.dist-info/RECORD
