Metadata-Version: 2.4
Name: hueclientrest
Version: 0.2.0
Summary: A Python REST client for interacting with Hadoop Hue's REST API
Author-email: Ramon LOPEZ <ramon.lopez@outlook.fr>
License: GPL-3.0
Project-URL: Homepage, https://github.com/SpanishST/HueClientRest
Project-URL: Repository, https://github.com/SpanishST/HueClientRest
Project-URL: Documentation, https://github.com/SpanishST/HueClientRest
Project-URL: Bug Reports, https://github.com/SpanishST/HueClientRest
Keywords: hue,hadoop,package,python
Classifier: Development Status :: 3 - Alpha
Classifier: Intended Audience :: Developers
Classifier: License :: OSI Approved :: MIT License
Classifier: Operating System :: OS Independent
Classifier: Programming Language :: Python :: 3
Classifier: Programming Language :: Python :: 3.9
Classifier: Programming Language :: Python :: 3.10
Classifier: Programming Language :: Python :: 3.11
Classifier: Programming Language :: Python :: 3.12
Requires-Python: >=3.9
License-File: LICENSE
Requires-Dist: requests<3.0.0,>=2.28.0
Requires-Dist: urllib3<3.0.0,>=1.26.0
Provides-Extra: dev
Requires-Dist: twine; extra == "dev"
Provides-Extra: docs
Dynamic: license-file
